{
    "Sheet1": [
        {
            "Countries": "Afghanistan"
        },
        {
            "Countries": "Albania"
        },
        {
            "Countries": "Algeria"
        },
        {
            "Countries": "Andorra"
        },
        {
            "Countries": "Angola"
        },
        {
            "Countries": "Antigua and Barbuda"
        },
        {
            "Countries": "Argentina"
        },
        {
            "Countries": "Armenia"
        },
        {
            "Countries": "Australia"
        },
        {
            "Countries": "Austria"
        },
        {
            "Countries": "Azerbaijan"
        },
        {
            "Countries": "Bahamas"
        },
        {
            "Countries": "Bahrain"
        },
        {
            "Countries": "Bangladesh"
        },
        {
            "Countries": "Barbados"
        },
        {
            "Countries": "Belarus"
        },
        {
            "Countries": "Belgium"
        },
        {
            "Countries": "Belize"
        },
        {
            "Countries": "Benin"
        },
        {
            "Countries": "Bhutan"
        },
        {
            "Countries": "Bolivia"
        },
        {
            "Countries": "Bosnia"
        },
        {
            "Countries": "Botswana"
        },
        {
            "Countries": "Brazil"
        },
        {
            "Countries": "Brunei"
        },
        {
            "Countries": "Bulgaria"
        },
        {
            "Countries": "Burkina Faso"
        },
        {
            "Countries": "Burundi"
        },
        {
            "Countries": "Cabo Verde"
        },
        {
            "Countries": "Cambodia"
        },
        {
            "Countries": "Cameroon"
        },
        {
            "Countries": "Canada"
        },
        {
            "Countries": "Central African Republic"
        },
        {
            "Countries": "Chad"
        },
        {
            "Countries": "Chile"
        },
        {
            "Countries": "China"
        },
        {
            "Countries": "Colombia"
        },
        {
            "Countries": "Comoros"
        },
        {
            "Countries": "Congo, Democratic Republic of the"
        },
        {
            "Countries": "Congo, Republic of the"
        },
        {
            "Countries": "Costa Rica"
        },
        {
            "Countries": "Cote d'Ivoire"
        },
        {
            "Countries": "Croatia"
        },
        {
            "Countries": "Cuba"
        },
        {
            "Countries": "Cyprus"
        },
        {
            "Countries": "Czechia"
        },
        {
            "Countries": "Denmark"
        },
        {
            "Countries": "Djibouti"
        },
        {
            "Countries": "Dominica"
        },
        {
            "Countries": "Dominican Republic"
        },
        {
            "Countries": "Ecuador"
        },
        {
            "Countries": "Egypt"
        },
        {
            "Countries": "El Salvador"
        },
        {
            "Countries": "Equatorial Guinea"
        },
        {
            "Countries": "Eritrea"
        },
        {
            "Countries": "Estonia"
        },
        {
            "Countries": "Eswatini"
        },
        {
            "Countries": "Ethiopia"
        },
        {
            "Countries": "Fiji"
        },
        {
            "Countries": "Finland"
        },
        {
            "Countries": "France"
        },
        {
            "Countries": "Gabon"
        },
        {
            "Countries": "Gambia"
        },
        {
            "Countries": "Georgia"
        },
        {
            "Countries": "Germany"
        },
        {
            "Countries": "Ghana"
        },
        {
            "Countries": "Greece"
        },
        {
            "Countries": "Grenada"
        },
        {
            "Countries": "Guatemala"
        },
        {
            "Countries": "Guinea"
        },
        {
            "Countries": "Guinea Bissau"
        },
        {
            "Countries": "Guyana"
        },
        {
            "Countries": "Haiti"
        },
        {
            "Countries": "Honduras"
        },
        {
            "Countries": "Hungary"
        },
        {
            "Countries": "Iceland"
        },
        {
            "Countries": "India"
        },
        {
            "Countries": "Indonesia"
        },
        {
            "Countries": "Iran"
        },
        {
            "Countries": "Iraq"
        },
        {
            "Countries": "Ireland"
        },
        {
            "Countries": "Israel"
        },
        {
            "Countries": "Italy"
        },
        {
            "Countries": "Jamaica"
        },
        {
            "Countries": "Japan"
        },
        {
            "Countries": "Jordan"
        },
        {
            "Countries": "Kazakhstan"
        },
        {
            "Countries": "Kenya"
        },
        {
            "Countries": "Kiribati"
        },
        {
            "Countries": "Kosovo"
        },
        {
            "Countries": "Kuwait"
        },
        {
            "Countries": "Kyrgyzstan"
        },
        {
            "Countries": "Laos"
        },
        {
            "Countries": "Latvia"
        },
        {
            "Countries": "Lebanon"
        },
        {
            "Countries": "Lesotho"
        },
        {
            "Countries": "Liberia"
        },
        {
            "Countries": "Libya"
        },
        {
            "Countries": "Liechtenstein"
        },
        {
            "Countries": "Lithuania"
        },
        {
            "Countries": "Luxembourg"
        },
        {
            "Countries": "Madagascar"
        },
        {
            "Countries": "Malawi"
        },
        {
            "Countries": "Malaysia"
        },
        {
            "Countries": "Maldives"
        },
        {
            "Countries": "Mali"
        },
        {
            "Countries": "Malta"
        },
        {
            "Countries": "Marshall Islands"
        },
        {
            "Countries": "Mauritania"
        },
        {
            "Countries": "Mauritius"
        },
        {
            "Countries": "Mexico"
        },
        {
            "Countries": "Micronesia"
        },
        {
            "Countries": "Moldova"
        },
        {
            "Countries": "Monaco"
        },
        {
            "Countries": "Mongolia"
        },
        {
            "Countries": "Montenegro"
        },
        {
            "Countries": "Morocco"
        },
        {
            "Countries": "Mozambique"
        },
        {
            "Countries": "Myanmar"
        },
        {
            "Countries": "Namibia"
        },
        {
            "Countries": "Nauru"
        },
        {
            "Countries": "Nepal"
        },
        {
            "Countries": "Netherlands"
        },
        {
            "Countries": "New Zealand"
        },
        {
            "Countries": "Nicaragua"
        },
        {
            "Countries": "Niger"
        },
        {
            "Countries": "Nigeria"
        },
        {
            "Countries": "North Korea"
        },
        {
            "Countries": "North Macedonia"
        },
        {
            "Countries": "Norway"
        },
        {
            "Countries": "Oman"
        },
        {
            "Countries": "Pakistan"
        },
        {
            "Countries": "Palau"
        },
        {
            "Countries": "Palestine"
        },
        {
            "Countries": "Panama"
        },
        {
            "Countries": "Papua New Guinea"
        },
        {
            "Countries": "Paraguay"
        },
        {
            "Countries": "Peru"
        },
        {
            "Countries": "Philippines"
        },
        {
            "Countries": "Poland"
        },
        {
            "Countries": "Portugal"
        },
        {
            "Countries": "Qatar"
        },
        {
            "Countries": "Romania"
        },
        {
            "Countries": "Russian"
        },
        {
            "Countries": "Rwanda"
        },
        {
            "Countries": "Saint Kitts and Nevis"
        },
        {
            "Countries": "Saint Lucia"
        },
        {
            "Countries": "Saint Vincent and the Grenadines"
        },
        {
            "Countries": "Samoa"
        },
        {
            "Countries": "San Marino"
        },
        {
            "Countries": "Sao Tome and Principe"
        },
        {
            "Countries": "Saudi Arabia"
        },
        {
            "Countries": "Senegal"
        },
        {
            "Countries": "Serbia"
        },
        {
            "Countries": "Seychelles"
        },
        {
            "Countries": "Sierra Leone"
        },
        {
            "Countries": "Singapore"
        },
        {
            "Countries": "Slovakia"
        },
        {
            "Countries": "Slovenia"
        },
        {
            "Countries": "Solomon Islands"
        },
        {
            "Countries": "Somalia"
        },
        {
            "Countries": "South Africa"
        },
        {
            "Countries": "South Korea"
        },
        {
            "Countries": "South Sudan"
        },
        {
            "Countries": "Spain"
        },
        {
            "Countries": "Sri Lanka"
        },
        {
            "Countries": "Sudan"
        },
        {
            "Countries": "Suriname"
        },
        {
            "Countries": "Sweden"
        },
        {
            "Countries": "Switzerland"
        },
        {
            "Countries": "Syria"
        },
        {
            "Countries": "Taiwan"
        },
        {
            "Countries": "Tajikistan"
        },
        {
            "Countries": "Tanzania"
        },
        {
            "Countries": "Thailand"
        },
        {
            "Countries": "Timor Leste"
        },
        {
            "Countries": "Togo"
        },
        {
            "Countries": "Tonga"
        },
        {
            "Countries": "Trinidad and Tobago"
        },
        {
            "Countries": "Tunisia"
        },
        {
            "Countries": "Turkey"
        },
        {
            "Countries": "Turkmenistan"
        },
        {
            "Countries": "Tuvalu"
        },
        {
            "Countries": "Uganda"
        },
        {
            "Countries": "Ukraine"
        },
        {
            "Countries": "United Arab Emirates"
        },
        {
            "Countries": "United Kingdom"
        },
        {
            "Countries": "United States of America"
        },
        {
            "Countries": "Uruguay"
        },
        {
            "Countries": "Uzbekistan"
        },
        {
            "Countries": "Vanuatu"
        },
        {
            "Countries": "Vatican City"
        },
        {
            "Countries": "Venezuela"
        },
        {
            "Countries": "Viet Nam"
        },
        {
            "Countries": "Yemen"
        },
        {
            "Countries": "Zambia"
        },
        {
            "Countries": "Zimbabwe"
        }
    ]
}
